{
    "name": "react-typescript-reason-training",
    "reason": {
        "react-jsx": 3
    },
    "sources": [
        {
            "dir": "src",
            "subdirs": true
        }
    ],
    "package-specs": [
        {
            "module": "es6-global",
            "in-source": true
        }
    ],
    "suffix": ".bs.js",
    "namespace": true,
    "bs-dependencies": [
        "reason-react",
        "@jsiebern/bs-material-ui",
        "@mscharley/bs-material-ui-icons"
    ],
    "refmt": 3,
    "gentypeconfig": {
        "language": "typescript"
    }
}
